dryg/__init__.py
dryg/settings.py
antar-0.0.1.dev0.dist-info/METADATA
antar-0.0.1.dev0.dist-info/WHEEL
antar-0.0.1.dev0.dist-info/top_level.txt
antar-0.0.1.dev0.dist-info/RECORD
