Metadata-Version: 2.1
Name: antar
Version: 0.0.1.dev0
Author: antar devs
Author-email: ayush.chaurarsia@gmail.com
Requires-Python: >=3.7
Requires-Dist: pygithub
Requires-Dist: lancedb
Requires-Dist: pyarrow
Requires-Dist: llama-cpp-python
Requires-Dist: huggingface-hub
Requires-Dist: sentencepiece
